ShareMount
