Metadata-Version: 1.0
Name: ShareMount
Version: 0.6b0.dev0
Summary: 
Home-page: UNKNOWN
Author: Darryl lane
Author-email: DarrylLane101@gmail.com
License: LICENSE
Platform: UNKNOWN
